whatsapp_business_api_Dipo_Cyborg/__init__.py
whatsapp_business_api_Dipo_Cyborg/whatsapp_business_api.py
whatsapp_business_api_dipo_cyborg-0.0.2.dist-info/METADATA
whatsapp_business_api_dipo_cyborg-0.0.2.dist-info/WHEEL
whatsapp_business_api_dipo_cyborg-0.0.2.dist-info/licenses/LICENSE
whatsapp_business_api_dipo_cyborg-0.0.2.dist-info/RECORD
